{"tg_targets":{"call#80.0 in handle_inotify_events":["_inotify_create","_inotify_delete","_inotify_ignored","_inotify_moved_from","_inotify_moved_to"],"call#80.0 in internal _traverse@src/daemon/index.c":["search"]},"tg_targets_argnum":{"call#80.0 in handle_inotify_events":["_inotify_create","_inotify_delete","_inotify_ignored","_inotify_moved_from","_inotify_moved_to"],"call#80.0 in internal _traverse@src/daemon/index.c":["search"]},"tg_targets_hash":{"call#80.0 in handle_inotify_events":["load","sext","getelementptr","getelementptr","load","load","load","load","call","store","br"],"call#80.0 in internal _traverse@src/daemon/index.c":["call","load","load","call","store","icmp","br"]}}
