{"tg_targets":{"call#80.0 in chunkgenCreate":["generatorGetBlock"],"call#80.0 in internal renderOnMouseHook@src/render.c":["onMouse"],"call#80.0 in internal worldrenderDrawSzene@src/worldrender.c":[],"call#80.0 in worldrenderInit":[],"call#80.1 in worldrenderInit":[],"call#80.2 in worldrenderInit":[],"call#80.3 in worldrenderInit":[],"call#80.4 in worldrenderInit":[],"call#80.5 in worldrenderInit":[]},"tg_targets_argnum":{"call#80.0 in chunkgenCreate":["generatorGetBlock"],"call#80.0 in internal renderOnMouseHook@src/render.c":["onMouse"],"call#80.0 in internal worldrenderDrawSzene@src/worldrender.c":[],"call#80.0 in worldrenderInit":[],"call#80.1 in worldrenderInit":[],"call#80.2 in worldrenderInit":[],"call#80.3 in worldrenderInit":[],"call#80.4 in worldrenderInit":[],"call#80.5 in worldrenderInit":[]},"tg_targets_hash":{"call#80.0 in chunkgenCreate":["load","getelementptr","store","load","getelementptr","load","bitcast","bitcast","call","getelementptr","load","getelementptr","load","call","load","getelementptr","store","load","getelementptr","store","br"],"call#80.0 in internal renderOnMouseHook@src/render.c":["load","load","load","load","call","br"],"call#80.0 in internal worldrenderDrawSzene@src/worldrender.c":["load","load","sext","mul","load","bitcast","call","load","store","call","store","br"],"call#80.0 in worldrenderInit":["call","load","call","call","call","getelementptr","store","getelementptr","store","getelementptr","store","getelementptr","store","getelementptr","call","getelementptr","store","getelementptr","store","getelementptr","store","getelementptr","store","getelementptr","call","call","getelementptr","store","getelementptr","store","getelementptr","store","getelementptr","store","getelementptr","call","call","call","call","call","load","call","load","call","load","load","call","load","load","call","call","call","call","call","bitcast","store","call","bitcast","store","call","store","br"],"call#80.1 in worldrenderInit":["call","load","call","call","call","getelementptr","store","getelementptr","store","getelementptr","store","getelementptr","store","getelementptr","call","getelementptr","store","getelementptr","store","getelementptr","store","getelementptr","store","getelementptr","call","call","getelementptr","store","getelementptr","store","getelementptr","store","getelementptr","store","getelementptr","call","call","call","call","call","load","call","load","call","load","load","call","load","load","call","call","call","call","call","bitcast","store","call","bitcast","store","call","store","br"],"call#80.2 in worldrenderInit":["call","load","call","call","call","getelementptr","store","getelementptr","store","getelementptr","store","getelementptr","store","getelementptr","call","getelementptr","store","getelementptr","store","getelementptr","store","getelementptr","store","getelementptr","call","call","getelementptr","store","getelementptr","store","getelementptr","store","getelementptr","store","getelementptr","call","call","call","call","call","load","call","load","call","load","load","call","load","load","call","call","call","call","call","bitcast","store","call","bitcast","store","call","store","br"],"call#80.3 in worldrenderInit":["call","load","call","call","call","getelementptr","store","getelementptr","store","getelementptr","store","getelementptr","store","getelementptr","call","getelementptr","store","getelementptr","store","getelementptr","store","getelementptr","store","getelementptr","call","call","getelementptr","store","getelementptr","store","getelementptr","store","getelementptr","store","getelementptr","call","call","call","call","call","load","call","load","call","load","load","call","load","load","call","call","call","call","call","bitcast","store","call","bitcast","store","call","store","br"],"call#80.4 in worldrenderInit":["load","call","load","load","bitcast","call","call","call","call","call","load","getelementptr","load","store","load","getelementptr","store","store","br"],"call#80.5 in worldrenderInit":["load","call","load","load","bitcast","call","call","call","call","call","load","getelementptr","load","store","load","getelementptr","store","store","br"]}}
