{"tg_targets":{"call#80.0 in internal process_desc@signpost.c":["default_params"],"call#80.0 in internal start_soak@signpost.c":["new_game_desc"],"call#80.0 in main":["default_params"],"call#80.1 in internal process_desc@signpost.c":["decode_params"],"call#80.1 in internal start_soak@signpost.c":["new_game"],"call#80.1 in main":["decode_params"],"call#80.2 in internal process_desc@signpost.c":["encode_params","validate_params"],"call#80.2 in internal start_soak@signpost.c":["free_game"],"call#80.2 in main":["encode_params","validate_params"],"call#80.3 in internal process_desc@signpost.c":["free_params"],"call#80.3 in main":["free_params"],"call#80.4 in internal process_desc@signpost.c":["validate_desc"],"call#80.4 in main":["encode_params","validate_params"],"call#80.5 in internal process_desc@signpost.c":["free_params"],"call#80.5 in main":["new_game_desc"],"call#80.6 in internal process_desc@signpost.c":["new_game"],"call#80.6 in main":["free_params"],"call#80.7 in internal process_desc@signpost.c":["solve_game"],"call#80.8 in internal process_desc@signpost.c":["free_game"],"call#80.9 in internal process_desc@signpost.c":["free_params"]},"tg_targets_argnum":{"call#80.0 in internal process_desc@signpost.c":["default_params"],"call#80.0 in internal start_soak@signpost.c":["new_game_desc"],"call#80.0 in main":["default_params"],"call#80.1 in internal process_desc@signpost.c":["decode_params"],"call#80.1 in internal start_soak@signpost.c":["new_game"],"call#80.1 in main":["decode_params"],"call#80.2 in internal process_desc@signpost.c":["encode_params","validate_params"],"call#80.2 in internal start_soak@signpost.c":["free_game"],"call#80.2 in main":["encode_params","validate_params"],"call#80.3 in internal process_desc@signpost.c":["free_params"],"call#80.3 in main":["free_params"],"call#80.4 in internal process_desc@signpost.c":["validate_desc"],"call#80.4 in main":["encode_params","validate_params"],"call#80.5 in internal process_desc@signpost.c":["free_params"],"call#80.5 in main":["new_game_desc"],"call#80.6 in internal process_desc@signpost.c":["new_game"],"call#80.6 in main":["free_params"],"call#80.7 in internal process_desc@signpost.c":["solve_game"],"call#80.8 in internal process_desc@signpost.c":["free_game"],"call#80.9 in internal process_desc@signpost.c":["free_params"]},"tg_targets_hash":{"call#80.0 in internal process_desc@signpost.c":["load","getelementptr","store","store","load","call","store","load","load","load","call","load","load","call","store","load","icmp","br"],"call#80.0 in internal start_soak@signpost.c":["load","load","call","trunc","call","store","load","load","load","call","store","load","load","load","call","store","store","br"],"call#80.0 in main":["call","load","call","store","load","icmp","br"],"call#80.1 in internal process_desc@signpost.c":["load","getelementptr","store","store","load","call","store","load","load","load","call","load","load","call","store","load","icmp","br"],"call#80.1 in internal start_soak@signpost.c":["load","load","call","trunc","call","store","load","load","load","call","store","load","load","load","call","store","store","br"],"call#80.1 in main":["load","load","load","call","br"],"call#80.2 in internal process_desc@signpost.c":["load","getelementptr","store","store","load","call","store","load","load","load","call","load","load","call","store","load","icmp","br"],"call#80.2 in internal start_soak@signpost.c":["load","load","call","load","call","load","call","load","call","load","add","store","call","store","load","load","icmp","br"],"call#80.2 in main":["load","load","call","store","load","icmp","br"],"call#80.3 in internal process_desc@signpost.c":["load","load","load","call","load","load","call","br"],"call#80.3 in main":["load","load","load","call","load","load","call","call","unreachable"],"call#80.4 in internal process_desc@signpost.c":["load","load","load","call","store","load","icmp","br"],"call#80.4 in main":["call","load","load","call","store","store","br"],"call#80.5 in internal process_desc@signpost.c":["load","load","load","load","call","load","load","call","br"],"call#80.5 in main":["load","load","load","call","store","load","load","call","load","call","load","call","load","call","br"],"call#80.6 in internal process_desc@signpost.c":["load","load","load","call","store","load","load","load","call","store","load","icmp","br"],"call#80.6 in main":["load","load","call","br"],"call#80.7 in internal process_desc@signpost.c":["load","load","load","call","store","load","load","load","call","store","load","icmp","br"],"call#80.8 in internal process_desc@signpost.c":["load","load","call","load","load","call","br"],"call#80.9 in internal process_desc@signpost.c":["load","load","call","load","load","call","br"]}}
