{"tg_targets":{"call#80.0 in ctrlp_disp":["orckit_atur3_start_ctrl_conn_hook"],"call#80.0 in decaps_gre":["encaps_gre","encaps_hdlc"],"call#80.0 in decaps_hdlc":["encaps_gre","encaps_hdlc"],"call#80.0 in dequeue_gre":["encaps_gre","encaps_hdlc"],"call#80.0 in pptp_call_destroy":["call_callback"],"call#80.0 in pptp_call_open":["orckit_atur3_build_hook"],"call#80.0 in pptp_conn_destroy":[],"call#80.0 in pptp_conn_open":["orckit_atur3_start_ctrl_conn_hook"],"call#80.0 in pptp_set_link":["orckit_atur3_set_link_hook"],"call#80.1 in ctrlp_disp":[],"call#80.1 in decaps_gre":["encaps_gre","encaps_hdlc"],"call#80.1 in decaps_hdlc":["encaps_gre","encaps_hdlc"],"call#80.2 in ctrlp_disp":[],"call#80.3 in ctrlp_disp":[],"call#80.4 in ctrlp_disp":[],"call#80.5 in ctrlp_disp":["call_callback"],"call#80.6 in ctrlp_disp":["call_callback"],"call#80.7 in ctrlp_disp":["call_callback"]},"tg_targets_argnum":{"call#80.0 in ctrlp_disp":["orckit_atur3_start_ctrl_conn_hook"],"call#80.0 in decaps_gre":["encaps_gre","encaps_hdlc"],"call#80.0 in decaps_hdlc":["encaps_gre","encaps_hdlc"],"call#80.0 in dequeue_gre":["encaps_gre","encaps_hdlc"],"call#80.0 in pptp_call_destroy":["call_callback"],"call#80.0 in pptp_call_open":["orckit_atur3_build_hook"],"call#80.0 in pptp_conn_destroy":[],"call#80.0 in pptp_conn_open":["orckit_atur3_start_ctrl_conn_hook"],"call#80.0 in pptp_set_link":["orckit_atur3_set_link_hook"],"call#80.1 in ctrlp_disp":[],"call#80.1 in decaps_gre":["encaps_gre","encaps_hdlc"],"call#80.1 in decaps_hdlc":["encaps_gre","encaps_hdlc"],"call#80.2 in ctrlp_disp":[],"call#80.3 in ctrlp_disp":[],"call#80.4 in ctrlp_disp":[],"call#80.5 in ctrlp_disp":["call_callback"],"call#80.6 in ctrlp_disp":["call_callback"],"call#80.7 in ctrlp_disp":["call_callback"]},"tg_targets_hash":{"call#80.0 in ctrlp_disp":["load","sext","getelementptr","getelementptr","load","call","store","icmp","br"],"call#80.0 in decaps_gre":["load","add","store","store","load","store","load","load","getelementptr","load","sext","getelementptr","load","zext","getelementptr","load","call","store","br"],"call#80.0 in decaps_hdlc":["load","load","getelementptr","load","call","store","icmp","br"],"call#80.0 in dequeue_gre":["load","getelementptr","load","store","load","load","load","getelementptr","load","load","getelementptr","load","call","store","load","call","load","icmp","br"],"call#80.0 in pptp_call_destroy":["load","getelementptr","load","load","load","call","br"],"call#80.0 in pptp_call_open":["load","sext","getelementptr","getelementptr","load","call","store","icmp","br"],"call#80.0 in pptp_conn_destroy":["load","getelementptr","load","load","call","br"],"call#80.0 in pptp_conn_open":["load","sext","getelementptr","getelementptr","load","call","store","icmp","br"],"call#80.0 in pptp_set_link":["call","load","sext","getelementptr","getelementptr","load","load","call","store","icmp","br"],"call#80.1 in ctrlp_disp":["load","getelementptr","load","load","call","br"],"call#80.1 in decaps_gre":["load","store","load","load","sub","sub","load","add","store","load","load","getelementptr","load","sext","getelementptr","load","zext","getelementptr","load","call","store","br"],"call#80.1 in decaps_hdlc":["load","zext","sub","trunc","store","load","load","load","call","store","icmp","br"],"call#80.2 in ctrlp_disp":["load","getelementptr","load","load","call","br"],"call#80.3 in ctrlp_disp":["load","getelementptr","load","load","call","br"],"call#80.4 in ctrlp_disp":["load","getelementptr","load","load","call","br"],"call#80.5 in ctrlp_disp":["load","getelementptr","load","load","load","call","br"],"call#80.6 in ctrlp_disp":["load","getelementptr","load","load","load","call","br"],"call#80.7 in ctrlp_disp":["load","getelementptr","load","load","load","call","br"]}}
