{"tg_targets":{"call#80.0 in internal sharebox_access@sharebox.c":["sharebox_access","slash_access"],"call#80.0 in internal sharebox_chmod@sharebox.c":["sharebox_chmod","sharebox_mkdir","slash_chmod","slash_mkdir"],"call#80.0 in internal sharebox_chown@sharebox.c":["sharebox_chown","slash_chown"],"call#80.0 in internal sharebox_getattr@sharebox.c":["sharebox_getattr","slash_getattr"],"call#80.0 in internal sharebox_mkdir@sharebox.c":["sharebox_chmod","sharebox_mkdir","slash_chmod","slash_mkdir"],"call#80.0 in internal sharebox_mknod@sharebox.c":["sharebox_mknod","slash_mknod"],"call#80.0 in internal sharebox_open@sharebox.c":["sharebox_open","sharebox_release","slash_open","slash_release"],"call#80.0 in internal sharebox_read@sharebox.c":["sharebox_read","slash_read"],"call#80.0 in internal sharebox_readdir@sharebox.c":["sharebox_readdir","slash_readdir"],"call#80.0 in internal sharebox_readlink@sharebox.c":["sharebox_readlink","slash_readlink"],"call#80.0 in internal sharebox_release@sharebox.c":["sharebox_open","sharebox_release","slash_open","slash_release"],"call#80.0 in internal sharebox_rename@sharebox.c":["sharebox_rename","sharebox_symlink","slash_rename","slash_symlink"],"call#80.0 in internal sharebox_rmdir@sharebox.c":["sharebox_rmdir","sharebox_unlink","slash_rmdir","slash_unlink"],"call#80.0 in internal sharebox_statfs@sharebox.c":["sharebox_statfs","slash_statfs"],"call#80.0 in internal sharebox_symlink@sharebox.c":["sharebox_rename","sharebox_symlink","slash_rename","slash_symlink"],"call#80.0 in internal sharebox_truncate@sharebox.c":["sharebox_truncate","slash_truncate"],"call#80.0 in internal sharebox_unlink@sharebox.c":["sharebox_rmdir","sharebox_unlink","slash_rmdir","slash_unlink"],"call#80.0 in internal sharebox_utimens@sharebox.c":["sharebox_utimens","slash_utimens"],"call#80.0 in internal sharebox_write@sharebox.c":["sharebox_write","slash_write"],"call#80.0 in internal slash_readdir@slash.c":[]},"tg_targets_argnum":{"call#80.0 in internal sharebox_access@sharebox.c":["sharebox_access","slash_access"],"call#80.0 in internal sharebox_chmod@sharebox.c":["sharebox_chmod","sharebox_mkdir","slash_chmod","slash_mkdir"],"call#80.0 in internal sharebox_chown@sharebox.c":["sharebox_chown","slash_chown"],"call#80.0 in internal sharebox_getattr@sharebox.c":["sharebox_getattr","slash_getattr"],"call#80.0 in internal sharebox_mkdir@sharebox.c":["sharebox_chmod","sharebox_mkdir","slash_chmod","slash_mkdir"],"call#80.0 in internal sharebox_mknod@sharebox.c":["sharebox_mknod","slash_mknod"],"call#80.0 in internal sharebox_open@sharebox.c":["sharebox_open","sharebox_release","slash_open","slash_release"],"call#80.0 in internal sharebox_read@sharebox.c":["sharebox_read","slash_read"],"call#80.0 in internal sharebox_readdir@sharebox.c":["sharebox_readdir","slash_readdir"],"call#80.0 in internal sharebox_readlink@sharebox.c":["sharebox_readlink","slash_readlink"],"call#80.0 in internal sharebox_release@sharebox.c":["sharebox_open","sharebox_release","slash_open","slash_release"],"call#80.0 in internal sharebox_rename@sharebox.c":["sharebox_rename","sharebox_symlink","slash_rename","slash_symlink"],"call#80.0 in internal sharebox_rmdir@sharebox.c":["sharebox_rmdir","sharebox_unlink","slash_rmdir","slash_unlink"],"call#80.0 in internal sharebox_statfs@sharebox.c":["sharebox_statfs","slash_statfs"],"call#80.0 in internal sharebox_symlink@sharebox.c":["sharebox_rename","sharebox_symlink","slash_rename","slash_symlink"],"call#80.0 in internal sharebox_truncate@sharebox.c":["sharebox_truncate","slash_truncate"],"call#80.0 in internal sharebox_unlink@sharebox.c":["sharebox_rmdir","sharebox_unlink","slash_rmdir","slash_unlink"],"call#80.0 in internal sharebox_utimens@sharebox.c":["sharebox_utimens","slash_utimens"],"call#80.0 in internal sharebox_write@sharebox.c":["sharebox_write","slash_write"],"call#80.0 in internal slash_readdir@slash.c":[]},"tg_targets_hash":{"call#80.0 in internal sharebox_access@sharebox.c":["load","getelementptr","getelementptr","load","load","load","call","store","br"],"call#80.0 in internal sharebox_chmod@sharebox.c":["load","getelementptr","getelementptr","load","load","load","call","store","br"],"call#80.0 in internal sharebox_chown@sharebox.c":["load","getelementptr","getelementptr","load","load","load","load","call","store","br"],"call#80.0 in internal sharebox_getattr@sharebox.c":["load","getelementptr","getelementptr","load","load","load","call","store","br"],"call#80.0 in internal sharebox_mkdir@sharebox.c":["load","getelementptr","getelementptr","load","load","load","call","store","br"],"call#80.0 in internal sharebox_mknod@sharebox.c":["load","getelementptr","getelementptr","load","load","load","load","call","store","br"],"call#80.0 in internal sharebox_open@sharebox.c":["load","getelementptr","getelementptr","load","load","load","call","store","br"],"call#80.0 in internal sharebox_read@sharebox.c":["load","getelementptr","getelementptr","load","load","load","load","load","load","call","store","br"],"call#80.0 in internal sharebox_readdir@sharebox.c":["load","getelementptr","getelementptr","load","load","load","load","load","load","call","store","br"],"call#80.0 in internal sharebox_readlink@sharebox.c":["load","getelementptr","getelementptr","load","load","load","load","call","store","br"],"call#80.0 in internal sharebox_release@sharebox.c":["load","getelementptr","getelementptr","load","load","load","call","store","br"],"call#80.0 in internal sharebox_rename@sharebox.c":["load","getelementptr","getelementptr","load","load","load","call","store","br"],"call#80.0 in internal sharebox_rmdir@sharebox.c":["load","getelementptr","getelementptr","load","load","call","store","br"],"call#80.0 in internal sharebox_statfs@sharebox.c":["load","getelementptr","getelementptr","load","load","load","call","store","br"],"call#80.0 in internal sharebox_symlink@sharebox.c":["load","getelementptr","getelementptr","load","load","load","call","store","br"],"call#80.0 in internal sharebox_truncate@sharebox.c":["load","getelementptr","getelementptr","load","load","load","call","store","br"],"call#80.0 in internal sharebox_unlink@sharebox.c":["load","getelementptr","getelementptr","load","load","call","store","br"],"call#80.0 in internal sharebox_utimens@sharebox.c":["load","getelementptr","getelementptr","load","load","load","call","store","br"],"call#80.0 in internal sharebox_write@sharebox.c":["load","getelementptr","getelementptr","load","load","load","load","load","load","call","store","br"],"call#80.0 in internal slash_readdir@slash.c":["load","load","load","getelementptr","getelementptr","call","icmp","br"]}}
